dolphin_logger/__init__.py
dolphin_logger/cli.py
dolphin_logger/config.py
dolphin_logger/core_proxy.py
dolphin_logger/logging_utils.py
dolphin_logger/main.py
dolphin_logger/server.py
dolphin_logger/upload.py
dolphin_logger-0.2.0.dist-info/METADATA
dolphin_logger-0.2.0.dist-info/WHEEL
dolphin_logger-0.2.0.dist-info/entry_points.txt
dolphin_logger-0.2.0.dist-info/top_level.txt
dolphin_logger-0.2.0.dist-info/RECORD
