Metadata-Version: 2.4
Name: dolphin-logger
Version: 0.2.0
Summary: A proxy server to log LLM requests and responses.
Author-email: Eric Hartford <ehartford@gmail.com>
Project-URL: Homepage, https://github.com/cognitivecomputations/dolphin-logger
Project-URL: Bug Tracker, https://github.com/cognitivecomputations/dolphin-logger/issues
Classifier: Programming Language :: Python :: 3
Classifier: License :: OSI Approved :: MIT License
Classifier: Operating System :: OS Independent
Requires-Python: >=3.8
Requires-Dist: flask
Requires-Dist: flask-cors
Requires-Dist: requests
Requires-Dist: anthropic
Requires-Dist: huggingface-hub
Provides-Extra: upload
Requires-Dist: datasets; extra == "upload"
